



//	Ajuda a la confeccio de codi en Bytecode. Practiques de MEC
//
//
//
//
//	Classe per les constants(variables) utilitzades a Metodes i Field al fer el show
//
//
//
//
//
//
//
//	Josep Suy, Marc Massot 		Ultima modificacio: 8 de maig de 2007
//
//
//
//



public class CMethod {

String[] MAP= new String[256];
Long[] OPS=new Long[256];


CMethod() {

MAP[0]="nop          ";
MAP[1]="aconst_null  ";
MAP[2]="iconst_m1    ";
MAP[3]="iconst_0     ";
MAP[4]="iconst_1     ";
MAP[5]="iconst_2     ";
MAP[6]="iconst_3     ";
MAP[7]="iconst_4     "; 
MAP[8]="iconst_5     ";  
MAP[9]="lconst_0     ";
MAP[10]="lconst_1     ";
MAP[11]="fconst_0     ";
MAP[12]="fconst_1     ";
MAP[13]="fconst_2     ";
MAP[14]="dconst_0     ";
MAP[15]="dconst_1     ";
MAP[16]="bipush       ";
MAP[17]="sipush       "; 
MAP[18]="ldc          ";
MAP[19]="ldc_w        ";
MAP[20]="ldc2_w       ";
MAP[21]="iload        ";
MAP[22]="lload        ";
MAP[23]="fload        ";
MAP[24]="dload        ";
MAP[25]="aload        ";
MAP[26]="iload_0      ";
MAP[27]="iload_1      "; 
MAP[28]="iload_2      "; 
MAP[29]="iload_3      ";
MAP[30]="lload_0      ";
MAP[31]="lload_1      ";
MAP[32]="lload_2      ";
MAP[33]="lload_3      ";
MAP[34]="fload_0      ";
MAP[35]="fload_1      ";
MAP[36]="fload_2      ";
MAP[37]="fload_3      ";
MAP[38]="dload_0      ";
MAP[39]="dload_1      ";
MAP[40]="dload_2      ";
MAP[41]="dload_3      ";
MAP[42]="aload_0      ";
MAP[43]="aload_1      ";
MAP[44]="aload_2      ";
MAP[45]="aload_3      ";
MAP[46]="iaload       ";
MAP[47]="laload       "; 
MAP[48]="faload       "; 
MAP[49]="daload       ";
MAP[50]="aaload       ";
MAP[51]="baload       ";
MAP[52]="caload       ";
MAP[53]="saload       ";
MAP[54]="istore       ";
MAP[55]="lstore       ";
MAP[56]="fstore       ";
MAP[57]="dstore       "; 
MAP[58]="astore       "; 
MAP[59]="istore_0     ";
MAP[60]="istore_1     ";
MAP[61]="istore_2     ";
MAP[62]="istore_3     ";
MAP[63]="lstore_0     ";
MAP[64]="lstore_1     ";
MAP[65]="lstore_2     ";
MAP[66]="lstore_3     ";
MAP[67]="fstore_0     "; 
MAP[68]="fstore_1     "; 
MAP[69]="fstore_2     ";
MAP[70]="fstore_3     ";
MAP[71]="dstore_0     ";
MAP[72]="dstore_1     ";
MAP[73]="dstore_2     ";
MAP[74]="dstore_3     ";
MAP[75]="astore_0     ";
MAP[76]="astore_1     ";
MAP[77]="astore_2     "; 
MAP[78]="astore_3     "; 
MAP[79]="iastore      ";
MAP[80]="lastore      ";
MAP[81]="fastore      ";
MAP[82]="dastore      ";
MAP[83]="aastore      ";
MAP[84]="bastore      ";
MAP[85]="castore      ";
MAP[86]="sastore      ";
MAP[87]="pop          ";
MAP[88]="pop2         ";
MAP[89]="dup          ";
MAP[90]="dup_x1       ";
MAP[91]="dup_x2       ";
MAP[92]="dup2         ";
MAP[93]="dup2_x1      ";
MAP[94]="dup2_x2      ";
MAP[95]="swap         ";
MAP[96]="iadd         ";
MAP[97]="ladd         "; 
MAP[98]="fadd         "; 
MAP[99]="dadd         ";
MAP[100]="isub         ";
MAP[101]="lsub         ";
MAP[102]="fsub         ";
MAP[103]="dsub         ";
MAP[104]="imul         ";
MAP[105]="lmul         ";
MAP[106]="fmul         ";
MAP[107]="dmul         "; 
MAP[108]="idiv         "; 
MAP[109]="ldiv         ";
MAP[110]="fdiv         ";
MAP[111]="ddiv         ";
MAP[112]="irem         ";
MAP[113]="lrem         ";
MAP[114]="frem         ";
MAP[115]="drem         ";
MAP[116]="ineg         ";
MAP[117]="lneg         "; 
MAP[118]="fneg         "; 
MAP[119]="dneg         ";
MAP[120]="ishl         ";
MAP[121]="lshl         ";
MAP[122]="ishr         ";
MAP[123]="lshr         ";
MAP[124]="iushr        ";
MAP[125]="lushr        ";
MAP[126]="iand         ";
MAP[127]="land         ";
MAP[128]="ior          ";
MAP[129]="lor          ";
MAP[130]="ixor         ";
MAP[131]="lxor         ";
MAP[132]="iinc         ";
MAP[133]="i2l          ";
MAP[134]="i2f          ";
MAP[135]="i2d          ";
MAP[136]="l2i          ";
MAP[137]="l2f          "; 
MAP[138]="l2d          "; 
MAP[139]="f2i          ";
MAP[140]="f2l          ";
MAP[141]="f2d          ";
MAP[142]="d2i          ";
MAP[143]="d2l          ";
MAP[144]="d2f          ";
MAP[145]="i2b          ";
MAP[146]="i2c          ";
MAP[147]="i2s          "; 
MAP[148]="lcmp         "; 
MAP[149]="fcmpl        ";
MAP[150]="fcmpg        ";
MAP[151]="dcmpl        ";
MAP[152]="dcmpg        ";
MAP[153]="ifeq         ";
MAP[154]="ifne         ";
MAP[155]="iflt         ";
MAP[156]="ifge         ";
MAP[157]="ifgt         ";
MAP[158]="ifle         "; 
MAP[159]="if_icmpeq    ";
MAP[160]="if_icmpne    ";
MAP[161]="if_icmplt    ";
MAP[162]="if_icmpge    ";
MAP[163]="if_icmpgt    ";
MAP[164]="if_icmple    ";
MAP[165]="if_acmpeq    ";
MAP[166]="if_acmpne    ";
MAP[167]="goto         "; 
MAP[168]="jsr          "; 
MAP[169]="ret          ";
MAP[170]="tableswitch  ";
MAP[171]="lookupswitch ";
MAP[172]="ireturn      ";
MAP[173]="lreturn      ";
MAP[174]="freturn      ";
MAP[175]="dreturn      ";
MAP[176]="areturn      ";
MAP[177]="return       "; 
MAP[178]="getstatic    "; 
MAP[179]="putstatic    ";
MAP[180]="getfield     ";
MAP[181]="putfield     ";
MAP[182]="invokevirtual";
MAP[183]="invokespecial";
MAP[184]="invokestatic ";
MAP[185]="invokeinterface";
MAP[186]="xxxunusedxxx ";
MAP[187]="new          "; 
MAP[188]="newarray     "; 
MAP[189]="anewarray    ";
MAP[190]="arraylength  ";
MAP[191]="athrow       ";
MAP[192]="checkcast    ";
MAP[193]="instanceof   ";
MAP[194]="monitorenter ";
MAP[195]="monitorexit  ";
MAP[196]="wide         ";
MAP[197]="multianewarray"; 
MAP[198]="ifnull       "; 
MAP[199]="ifnonnull    ";
MAP[200]="goto_w       ";
MAP[201]="jsr_w        ";
MAP[202]="breakpoint   ";
MAP[203]="ldc_quick    ";
MAP[204]="ldc_w_quick  ";
MAP[205]="ldc2_w_quick ";
MAP[206]="getfield_quick";
MAP[207]="putfield_quick"; 
MAP[208]="getfield2_quick"; 
MAP[209]="putfield2_quick";
MAP[210]="getstatic_quick";
MAP[211]="putstatic_quick";
MAP[212]="getstatic2_quick";
MAP[213]="putstatic2_quick";
MAP[214]="invokevirtual_quick";
MAP[215]="invokenonvirtual_quick";
MAP[216]="invokesuper_quick";
MAP[217]="invokestatic_quick"; 
MAP[218]="invokeinterface_quick"; 
MAP[219]="invokevirtualobject_quick";
MAP[220]="new_quick    ";
MAP[221]="anewarray_quick";
MAP[222]="multianewarray_quick";
MAP[223]="checkcast_quick";
MAP[224]="instanceof_quick";
MAP[225]="invokevirtual_quick_w";
MAP[226]="getfield_quick_w";
MAP[227]="putfield_quick_w"; 
MAP[228]="";
MAP[229]="";MAP[230]="";MAP[231]="";MAP[232]="";MAP[233]="";MAP[234]="";MAP[235]="";MAP[236]="";MAP[237]="";MAP[238]="";
MAP[239]="";MAP[240]="";MAP[241]="";MAP[242]="";MAP[243]="";MAP[244]="";MAP[245]="";MAP[246]="";MAP[247]="";MAP[248]="";
MAP[249]="";MAP[250]="";MAP[251]="";MAP[252]="";MAP[253]="";
MAP[254]="impdep1      ";
MAP[255]="impdep2      ";









OPS[0]=0L;//"NOP";
OPS[1]=0L;//"ACONST_NULL";
OPS[2]=0L;//"ICONST_M1";
OPS[3]=0L;//"ICONST_0";
OPS[4]=0L;//"ICONST_1";
OPS[5]=0L;//"ICONST_2";
OPS[6]=0L;//"ICONST_3";
OPS[7]=0L;//"ICONST_4"; 
OPS[8]=0L;//"ICONST_5";  
OPS[9]=0L;//"LCONST_0";
OPS[10]=0L;//"LCONST_1";
OPS[11]=0L;//"FCONST_0";
OPS[12]=0L;//"FCONST_1";
OPS[13]=0L;//"FCONST_2";
OPS[14]=0L;//"DCONST_0";
OPS[15]=0L;//"DCONST_1";
OPS[16]=1L;//"BIPUSH";
OPS[17]=2L;//"SIPUSH"; 
OPS[18]=1L;//"LDC";
OPS[19]=2L;//"LDC_W";
OPS[20]=2L;//"LDC2_W";
OPS[21]=1L;//"ILOAD";
OPS[22]=1L;//"LLOAD";
OPS[23]=1L;//"FLOAD";
OPS[24]=1L;//"DLOAD";
OPS[25]=1L;//"ALOAD";
OPS[26]=0L;//"ILOAD_0";
OPS[27]=0L;//"ILOAD_1"; 
OPS[28]=0L;//"ILOAD_2"; 
OPS[29]=0L;//"ILOAD_3";
OPS[30]=0L;//"LLOAD_0";
OPS[31]=0L;//"LLOAD_1";
OPS[32]=0L;//"LLOAD_2";
OPS[33]=0L;//"LLOAD_3";
OPS[34]=0L;//"FLOAD_0";
OPS[35]=0L;//"FLOAD_1";
OPS[36]=0L;//"FLOAD_2";
OPS[37]=0L;//"FLOAD_3";
OPS[38]=0L;//"DLOAD_0";
OPS[39]=0L;//"DLOAD_1";
OPS[40]=0L;//"DLOAD_2";
OPS[41]=0L;//"DLOAD_3";
OPS[42]=0L;//"ALOAD_0";
OPS[43]=0L;//"ALOAD_1";
OPS[44]=0L;//"ALOAD_2";
OPS[45]=0L;//"ALOAD_3";
OPS[46]=0L;//"IALOAD";
OPS[47]=0L;//"LALOAD"; 
OPS[48]=0L;//"FALOAD"; 
OPS[49]=0L;//"DALOAD";
OPS[50]=0L;//"AALOAD";
OPS[51]=0L;//"BALOAD";
OPS[52]=0L;//"CALOAD";
OPS[53]=0L;//"SALOAD";
OPS[54]=1L;//"ISTORE";
OPS[55]=1L;//"LSTORE";
OPS[56]=1L;//"FSTORE";
OPS[57]=1L;//"DSTORE"; 
OPS[58]=1L;//"ASTORE"; 
OPS[59]=0L;//"ISTORE_0";
OPS[60]=0L;//"ISTORE_1";
OPS[61]=0L;//"ISTORE_2";
OPS[62]=0L;//"ISTORE_3";
OPS[63]=0L;//"LSTORE_0";
OPS[64]=0L;//"LSTORE_1";
OPS[65]=0L;//"LSTORE_2";
OPS[66]=0L;//"LSTORE_3";
OPS[67]=0L;//"FSTORE_0"; 
OPS[68]=0L;//"FSTORE_1"; 
OPS[69]=0L;//"FSTORE_2";
OPS[70]=0L;//"FSTORE_3";
OPS[71]=0L;//"DSTORE_0";
OPS[72]=0L;//"DSTORE_1";
OPS[73]=0L;//"DSTORE_2";
OPS[74]=0L;//"DSTORE_3";
OPS[75]=0L;//"ASTORE_0";
OPS[76]=0L;//"ASTORE_1";
OPS[77]=0L;//"ASTORE_2"; 
OPS[78]=0L;//"ASTORE_3"; 
OPS[79]=0L;//"IASTORE";
OPS[80]=0L;//"LASTORE";
OPS[81]=0L;//"FASTORE";
OPS[82]=0L;//"DASTORE";
OPS[83]=0L;//"AASTORE";
OPS[84]=0L;//"BASTORE";
OPS[85]=0L;//"CASTORE";
OPS[86]=0L;//"SASTORE";
OPS[87]=0L;//"POP";
OPS[88]=0L;//"POP2";
OPS[89]=0L;//"DUP";
OPS[90]=0L;//"DUP_X1";
OPS[91]=0L;//"DUP_X2";
OPS[92]=0L;//"DUP2";
OPS[93]=0L;//"DUP2_X1";
OPS[94]=0L;//"DUP2_X2";
OPS[95]=0L;//"SWAP";
OPS[96]=0L;//"IADD";
OPS[97]=0L;//"LADD"; 
OPS[98]=0L;//"FADD"; 
OPS[99]=0L;//"DADD";
OPS[100]=0L;//"ISUB";
OPS[101]=0L;//"LSUB";
OPS[102]=0L;//"FSUB";
OPS[103]=0L;//"DSUB";
OPS[104]=0L;//"IMUL";
OPS[105]=0L;//"LMUL";
OPS[106]=0L;//"FMUL";
OPS[107]=0L;//"DMUL"; 
OPS[108]=0L;//"IDIV"; 
OPS[109]=0L;//"LDIV";
OPS[110]=0L;//"FDIV";
OPS[111]=0L;//"DDIV";
OPS[112]=0L;//"IREM";
OPS[113]=0L;//"LREM";
OPS[114]=0L;//"FREM";
OPS[115]=0L;//"DREM";
OPS[116]=0L;//"INEG";
OPS[117]=0L;//"LNEG"; 
OPS[118]=0L;//"FNEG"; 
OPS[119]=0L;//"DNEG";
OPS[120]=0L;//"ISHL";
OPS[121]=0L;//"LSHL";
OPS[122]=0L;//"ISHR";
OPS[123]=0L;//"LSHR";
OPS[124]=0L;//"IUSHR";
OPS[125]=0L;//"LUSHR";
OPS[126]=0L;//"IAND";
OPS[127]=0L;//"LAND";
OPS[128]=0L;//"IOR";
OPS[129]=0L;//"LOR";
OPS[130]=0L;//"IXOR";
OPS[131]=0L;//"LXOR";
OPS[132]=2L;//"IINC";
OPS[133]=0L;//"I2L";
OPS[134]=0L;//"I2F";
OPS[135]=0L;//"I2D";
OPS[136]=0L;//"L2I";
OPS[137]=0L;//"L2F"; 
OPS[138]=0L;//"L2D"; 
OPS[139]=0L;//"F2I";
OPS[140]=0L;//"F2L";
OPS[141]=0L;//"F2D";
OPS[142]=0L;//"D2I";
OPS[143]=0L;//"D2L";
OPS[144]=0L;//"D2F";
OPS[145]=0L;//"I2B";
OPS[146]=0L;//"I2C";
OPS[147]=0L;//"I2S"; 
OPS[148]=0L;//"LCMP"; 
OPS[149]=0L;//"FCMPL";
OPS[150]=0L;//"FCMPG";
OPS[151]=0L;//"DCMPL";
OPS[152]=0L;//"DCMPG";
OPS[153]=2L;//"IFEQ";
OPS[154]=2L;//"IFNE";
OPS[155]=2L;//"IFLT";
OPS[156]=2L;//"IFGE";
OPS[157]=2L;//"IFGT";
OPS[158]=2L;//"IFLE"; 
OPS[159]=2L;//"IF_ICMPEQ";
OPS[160]=2L;//"IF_ICMPNE";
OPS[161]=2L;//"IF_ICMPLT";
OPS[162]=2L;//"IF_ICMPGE";
OPS[163]=2L;//"IF_ICMPGT";
OPS[164]=2L;//"IF_ICMPLE";
OPS[165]=2L;//"IF_ACMPEQ";
OPS[166]=2L;//"IF_ACMPNE";
OPS[167]=2L;//"GOTO"; 
OPS[168]=2L;//"JSR"; 
OPS[169]=1L;//"RET";
OPS[170]=-1L;//"TABLESWITCH";
OPS[171]=-1L;//"LOOKUPSWITCH";
OPS[172]=0L;//"IRETURN";
OPS[173]=0L;//"LRETURN";
OPS[174]=0L;//"FRETURN";
OPS[175]=0L;//"DRETURN";
OPS[176]=0L;//"ARETURN";
OPS[177]=0L;//"RETURN"; 
OPS[178]=2L;//"GETSTATIC"; 
OPS[179]=2L;//"PUTSTATIC";
OPS[180]=2L;//"GETFIELD";
OPS[181]=2L;//"PUTFIELD";
OPS[182]=2L;//"INVOKEVIRTUAL";
OPS[183]=2L;//"INVOKESPECIAL";
OPS[184]=2L;//"INVOKESTATIC";
OPS[185]=4L;//"INVOKEINTERFACE";
OPS[186]=0L;//"XXXUNUSEDXXX";
OPS[187]=2L;//"NEW"; 
OPS[188]=1L;//"NEWARRAY"; 
OPS[189]=2L;//"ANEWARRAY";
OPS[190]=0L;//"ARRAYLENGTH";
OPS[191]=0L;//"ATHROW";
OPS[192]=2L;//"CHECKCAST";
OPS[193]=2L;//"INSTANCEOF";
OPS[194]=0L;//"MONITORENTER";
OPS[195]=0L;//"MONITOREXIT";
OPS[196]=-1L;//"WIDE";
OPS[197]=3L;//"MULTIANEWARRAY"; 
OPS[198]=2L;//"IFNULL"; 
OPS[199]=2L;//"IFNONNULL";
OPS[200]=4L;//"GOTO_W";
OPS[201]=4L;//"JSR_W";
OPS[202]=0L;//"BREAKPOINT";
OPS[203]=1L;//"LDC_QUICK";
OPS[204]=2L;//"LDC_W_QUICK";
OPS[205]=2L;//"LDC2_W_QUICK";
OPS[206]=2L;//"GETFIELD_QUICK";
OPS[207]=2L;//"PUTFIELD_QUICK"; 
OPS[208]=2L;//"GETFIELD2_QUICK"; 
OPS[209]=2L;//"PUTFIELD2_QUICK";
OPS[210]=2L;//"GETSTATIC_QUICK";
OPS[211]=2L;//"PUTSTATIC_QUICK";
OPS[212]=2L;//"GETSTATIC2_QUICK";
OPS[213]=2L;//"PUTSTATIC2_QUICK";
OPS[214]=2L;//"INVOKEVIRTUAL_QUICK";
OPS[215]=2L;//"INVOKENONVIRTUAL_QUICK";
OPS[216]=2L;//"INVOKESUPER_QUICK";
OPS[217]=2L;//"INVOKESTATIC_QUICK"; 
OPS[218]=4L;//"INVOKEINTERFACE_QUICK"; 
OPS[219]=2L;//"INVOKEVIRTUALOBJECT_QUICK";
OPS[220]=2L;//"NEW_QUICK";
OPS[221]=2L;//"ANEWARRAY_QUICK";
OPS[222]=3L;//"MULTIANEWARRAY_QUICK";
OPS[223]=2L;//"CHECKCAST_QUICK";
OPS[224]=2L;//"INSTANCEOF_QUICK";
OPS[225]=2L;//"INVOKEVIRTUAL_QUICK_W";
OPS[226]=2L;//"GETFIELD_QUICK_W";
OPS[227]=2L;//"PUTFIELD_QUICK_W"; 
OPS[228]=0L;//"";
OPS[229]=0L;OPS[230]=0L;OPS[231]=0L;OPS[232]=0L;OPS[233]=0L;OPS[234]=0L;OPS[235]=0L;OPS[236]=0L;OPS[237]=0L;OPS[238]=0L;//"";"";"";"";"";"";"";"";"";"";
OPS[239]=0L;OPS[240]=0L;OPS[241]=0L;OPS[242]=0L;OPS[243]=0L;OPS[244]=0L;OPS[245]=0L;OPS[246]=0L;OPS[247]=0L;OPS[248]=0L;//"";"";"";"";"";"";"";"";"";"";
OPS[249]=0L;OPS[250]=0L;OPS[251]=0L;OPS[252]=0L;OPS[253]=0L;//"";"";"";"";
OPS[254]=0L;//"IMPDEP1";
OPS[255]=0L;//"IMPDEP2"


}



}
